tmux_conf/__init__.py
tmux_conf/constants.py
tmux_conf/exceptions.py
tmux_conf/py.typed
tmux_conf/tmux_conf.py
tmux_conf/utils.py
tmux_conf/vers_check.py
tmux_conf/embeded_scripts/__init__.py
tmux_conf/embeded_scripts/builder.py
tmux_conf/embeded_scripts/config.py
tmux_conf/embeded_scripts/emitter.py
tmux_conf/embeded_scripts/registry.py
tmux_conf/embeded_scripts/scripts.py
tmux_conf/embeded_scripts/spec.py
tmux_conf/plugins/__init__.py
tmux_conf/plugins/deployment.py
tmux_conf/plugins/display.py
tmux_conf/plugins/manager.py
tmux_conf/plugins/registry.py
tmux_conf-0.22.1.dist-info/licenses/LICENSE
tmux_conf-0.22.1.dist-info/METADATA
tmux_conf-0.22.1.dist-info/WHEEL
tmux_conf-0.22.1.dist-info/top_level.txt
tmux_conf-0.22.1.dist-info/RECORD
