Metadata-Version: 2.4
Name: tmux_conf
Version: 0.22.1
Summary: Generates version checked tmux conf
Author-email: Jacob Lundqvist <Jacob.Lundqvist@gmail.com>
Project-URL: Homepage, https://github.com/jaclu/tmux-conf
Project-URL: Documentation, https://github.com/jaclu/tmux-conf
Project-URL: Repository, https://github.com/jaclu/tmux-conf
Project-URL: Bug Tracker, https://github.com/jaclu/tmux-conf/issues
Keywords: tmux,automation
Classifier: Programming Language :: Python :: 3
Classifier: License :: OSI Approved :: MIT License
Classifier: Operating System :: OS Independent
Requires-Python: >=3.10
License-File: LICENSE
Dynamic: license-file
